{
  "/uk": "/",
  "/visquanta-team": "/team",
  "/dealer-success-solutions": "/dealer-success",
  "/dealer-success/dealer-success-solutions": "/dealer-success",
  "/auto-master-suite-technical-guides": "/ams-guides",
  "/promo": "/auto-master-suite",
  "/lead-loss-mitigation": "/lead-reactivation",
  "/lead-reactivation.com/lead-loss-mitigation": "/lead-reactivation",
  "/case-studies/westline-motors": "/case-studies",
  "/how-it-works": "/",
  "/faq": "/faqs",
  "/blog/promax-visquanta-partner": "/blog",
  "/enterprise-groups": "/dealers/auto-groups",
  "/dealers/auto-groupsnta.com/enterprise-groups": "/dealers/auto-groups",
  "/partnerships": "/book-demo",
  "/book-demoisquanta.com/partnerships": "/book-demo",
  "/blog-home": "/blog",
  "/blogw.visquanta.com/blog-home": "/blog",
  "/independent-dealers": "/dealers/independent",
  "/independent-dealerships": "/dealers/independent",
  "/pre-owned-dealerships": "/dealers/pre-owned",
  "/dealers/independenta.com/independent-dealers": "/dealers/independent",
  "/independent": "/dealers/independent",
  "/auto-group": "/dealers/auto-groups",
  "/dealers/auto-groups.visquanta.com/auto-group": "/dealers/auto-groups",
  "/auto-groups": "/dealers/auto-groups",
  "/franchise-dealers": "/dealers/franchise",
  "/franchise-dealerships": "/dealers/franchise",
  "/rv-dealerships": "/dealers/franchise",
  "/dealers/franchisenta.com/franchise-dealers": "/dealers/franchise",
  "/franchise": "/dealers/franchise",
  "/blog/sms-vs-email-vs-ai-chatbot-the-ultimate-guide-for-car-dealerships": "/blog/sms-vs-email-vs-ai-chatbot-the-ultimate-guide-for-dealerships",
  "/blog/5-reasons-car-buyers-prefer-sms-over-phone-calls-in-2025": "/blog/5-reasons-car-buyers-prefer-sms-over-phone-calls-from-dealerships",
  "/blog/why-every-dealership-needs-ai-for-lead-reactivation-in-2025": "/blog/why-every-dealership-needs-ai-for-lead-reactivation-in-2026",
  "/blog/why-every-dealership-needs-ai-for-lead-reactivation-in-2026lead-reactivation-in-2025": "/blog/why-every-dealership-needs-ai-for-lead-reactivation-in-2026",
  "/enterprise": "/dealers/auto-groups",
  "/landing-page": "/",
  "/leveraging-ai-for-lead-generation": "/lead-reactivation",
  "/leveraging-ai-for-lead-generation/": "/lead-reactivation",
  "/home": "/",
  "/homepage": "/",
  "/about-us": "/about-visquanta",
  "/contact-us": "/contact",
  "/case-study": "/case-studies",
  "/our-blog": "/blog",
  "/automotive": "/dealer-success",
  "/database-reactivation": "/lead-reactivation",
  "/ai-powered-email": "/speed-to-lead",
  "/advertising-lead-generation": "/custom-campaigns",
  "/service-drive-pro": "/service-drive",
  "/calendarbooking": "/book-demo",
  "/html-sitemap": "/sitemap.xml",
  "/html-sitemap/": "/sitemap.xml",
  "/visquanta-dealership": "/dealer-success",
  "/case-studies/cityline-auto-group-accelerates-sales-with-visquantas-automaster-suite": "/case-studies",
  "/case-studies/riverside-auto-mall-boosts-lead-conversion-with-visquantas-ai-automation": "/case-studies"
}